irclogger-0.0.2.dist-info/metadata.json
irclogger-0.0.2.dist-info/top_level.txt
irclogger-0.0.2.dist-info/RECORD
irclogger-0.0.2.dist-info/WHEEL
irclogger-0.0.2.dist-info/entry_points.txt
irclogger-0.0.2.dist-info/DESCRIPTION.rst
irclogger-0.0.2.dist-info/METADATA
irclogger/__init__.py
irclogger/main.py
