Metadata-Version: 2.0
Name: irclogger
Version: 0.0.2
Summary: Python IRC Logger Daemon
Home-page: https://bitbucket.org/prologic/irclogger
Author: James Mills
Author-email: James Mills, prologic at shortcircuit dot net dot au
License: MIT
Download-URL: 0.0.2/get/0.0.2.zip
Keywords: Python IRC Logger Daemon
Platform: POSIX
Requires-Dist: circuits
